slugify_fr/__init__.py
slugify_fr/core.py
slugify_fr-0.1.0.dist-info/METADATA
slugify_fr-0.1.0.dist-info/WHEEL
slugify_fr-0.1.0.dist-info/top_level.txt
slugify_fr-0.1.0.dist-info/RECORD
